{
    "type": "minecraft:crafting_shaped",
    "pattern": [
        "#DU",
        " / ",
        " / "
    ],
    "key": {
        "#": {
            "item": "extendedtools:pickaxesilver"
        },
        "D": {
            "item": "extendedtools:shovelsilver"
        },
        "U": {
            "item": "extendedtools:axesilver"
        },
        "/": {
            "item": "minecraft:stick"
        }
    },
    "result": {
        "id": "extendedtools:paxelsilver",
        "count": 1
    }
}